{"name":"analytics-service","className":"ModuleScript","filePaths":["src\\init.luau","build.project.json"],"children":[{"name":"Processor","className":"ModuleScript","filePaths":["src\\Processor\\init.luau"],"children":[{"name":"GlobalCCU","className":"ModuleScript","filePaths":["src\\Processor\\GlobalCCU.luau"]},{"name":"Queue","className":"ModuleScript","filePaths":["src\\Processor\\Queue.luau"]},{"name":"StepPrecedence","className":"ModuleScript","filePaths":["src\\Processor\\StepPrecedence.luau"]}]},{"name":"Types","className":"ModuleScript","filePaths":["src\\Types.luau"]}]}